colourswatch/__init__.py
colourswatch/colourswatch.py
colourswatch/gimpgplpal.py
colourswatch/io.py
colourswatch-2024.2.dist-info/LICENSE.md
colourswatch-2024.2.dist-info/METADATA
colourswatch-2024.2.dist-info/WHEEL
colourswatch-2024.2.dist-info/RECORD
