Metadata-Version: 2.1
Name: colourswatch
Version: 2024.2
Summary: Use this module to read, and write to a number of colour palette file formats
Home-page: https://github.com/FHPythonUtils/ColourSwatch
License: MIT
Author: FredHappyface
Requires-Python: >=3.9,<4.0
Classifier: Development Status :: 5 - Production/Stable
Classifier: Intended Audience :: Developers
Classifier: Intended Audience :: Education
Classifier: License :: OSI Approved :: MIT License
Classifier: Natural Language :: English
Classifier: Operating System :: OS Independent
Classifier: Programming Language :: Python :: 3
Classifier: Programming Language :: Python :: 3.9
Classifier: Programming Language :: Python :: 3.10
Classifier: Programming Language :: Python :: 3.11
Classifier: Programming Language :: Python :: 3.12
Classifier: Programming Language :: Python :: Implementation :: CPython
Classifier: Topic :: Multimedia :: Graphics
Classifier: Topic :: Software Development :: Libraries :: Python Modules
Classifier: Topic :: Utilities
Requires-Dist: Pillow (>=10.2.0,<11)
Requires-Dist: PyYAML (>=6.0.1,<7)
Requires-Dist: colormath (>=3.0.0,<4)
Requires-Dist: defusedxml (>=0.7.1,<2)
Requires-Dist: swatch (>=0.4.0,<2)
Requires-Dist: tomli (>=2.0.1,<3)
Requires-Dist: tomlkit (>=0.12.4,<2)
Project-URL: Documentation, https://github.com/FHPythonUtils/ColourSwatch/blob/master/README.md
Project-URL: Repository, https://github.com/FHPythonUtils/ColourSwatch
